{
  "": "",
  " ": " ",
  "About us": "About us",
  "Lang": "Lang",
  "Main page": "Main page",
  "Not Found Page": "Not Found Page",
  "age": "age",
  "cancel": "cancel",
  "city": "city",
  "counter": {
    "decrement": "decrement",
    "increment": "increment"
  },
  "country": {
    "label": ""
  },
  "currency": {
    "label": ""
  },
  "edit": "edit",
  "error": {
    "button": "button",
    "message": "message",
    "text": "text",
    "title": "title"
  },
  "firstName": "firstName",
  "header": {
    "about": "about",
    "login": "login",
    "logout": "logout",
    "main": "main"
  },
  "increment": "increment",
  "lang": "lang",
  "lastName": "lastName",
  "login": {
    "enter": {
      "password": "password",
      "username": "username"
    },
    "modal": {
      "error": "error",
      "title": "title"
    }
  },
  "profile": {
    "error": "error",
    "text": "text"
  },
  "save": "save",
  "sidebar": {
    "about": "about",
    "button": "button",
    "main": "main"
  },
  "title": "title",
  "Главная": "Главная",
  "О сайте": "О сайте"
}
